Metadata-Version: 2.1
Name: imply
Version: 1.0a3
Summary: Command line interface for analyzing Python imports.
Home-page: UNKNOWN
Author: David Seddon
Author-email: david@seddonym.me
License: BSD 2-Clause License
Project-URL: Source code, https://github.com/seddonym/imply/
Platform: UNKNOWN
Classifier: Development Status :: 3 - Alpha
Classifier: Intended Audience :: Developers
Classifier: License :: OSI Approved :: BSD License
Classifier: Operating System :: Unix
Classifier: Operating System :: POSIX
Classifier: Operating System :: Microsoft :: Windows
Classifier: Programming Language :: Python
Classifier: Programming Language :: Python :: 3.6
Classifier: Programming Language :: Python :: 3.7
Classifier: Programming Language :: Python :: Implementation :: CPython
Classifier: Topic :: Utilities
